prasar/__init__.py
prasar/prasar.py
prasar/prasar_logger.py
Prasar-1.2.1.dist-info/LICENSE
Prasar-1.2.1.dist-info/METADATA
Prasar-1.2.1.dist-info/WHEEL
Prasar-1.2.1.dist-info/top_level.txt
Prasar-1.2.1.dist-info/RECORD
