Metadata-Version: 2.1
Name: Prasar
Version: 1.2.1
Summary: A robust event handling framework for Python
Home-page: https://github.com/mishrababhishek/prasar
Author: Abhishek Mishra
Author-email: mishraabhishek.2899@gmail.com
Classifier: Programming Language :: Python :: 3
Classifier: License :: OSI Approved :: MIT License
Classifier: Operating System :: OS Independent
Requires-Python: >=3.7
License-File: LICENSE
Requires-Dist: colorama
